{"main/tabs/sofa":{"isFragment":true,"asStarter":false,"needLogin":false,"pageUrl":"main/tabs/sofa","className":"com.hongx.ppjoke.ui.sofa.SofaFragment","id":430054352},"main/tabs/home":{"isFragment":true,"asStarter":true,"needLogin":false,"pageUrl":"main/tabs/home","className":"com.hongx.ppjoke.ui.home.HomeFragment","id":1228822736},"main/tabs/publish":{"isFragment":false,"asStarter":false,"needLogin":true,"pageUrl":"main/tabs/publish","className":"com.hongx.ppjoke.ui.publish.PublishActivity","id":612129905},"main/tabs/find":{"isFragment":true,"asStarter":false,"needLogin":false,"pageUrl":"main/tabs/find","className":"com.hongx.ppjoke.ui.find.FindFragment","id":1446866672},"main/tabs/my":{"isFragment":true,"asStarter":false,"needLogin":true,"pageUrl":"main/tabs/my","className":"com.hongx.ppjoke.ui.my.MyFragment","id":839924336}}